pywakit/__init__.py
pywakit/whatsapp.py
pywakit-0.0.6.dist-info/LICENSE
pywakit-0.0.6.dist-info/METADATA
pywakit-0.0.6.dist-info/WHEEL
pywakit-0.0.6.dist-info/top_level.txt
pywakit-0.0.6.dist-info/RECORD
