Metadata-Version: 2.1
Name: pywakit
Version: 0.0.6
Summary: Automate the sending process of message in whatsapp through selenium
Home-page: https://github.com/y-agg/pywakit
Author: Yash Aggarwal
Author-email: yash.aggarwal.7545@gmail.com
Maintainer: Yash Aggarwal
License: MIT
Keywords: Send whatsapp message,message,auto,whatsapp,selenium,info
Platform: UNKNOWN
Classifier: License :: OSI Approved :: MIT License
Classifier: Programming Language :: Python
Classifier: Programming Language :: Python :: 3
Classifier: Programming Language :: Python :: 3.4
Classifier: Programming Language :: Python :: 3.5
Classifier: Programming Language :: Python :: 3.6
Classifier: Programming Language :: Python :: 3.7
Requires-Python: !=3.0.*, !=3.2.*, !=3.3.*, !=3.5.*, !=3.6.*, !=3.7.*
Requires-Dist: chardet (==3.0.4)
Requires-Dist: clint (==0.5.1)
Requires-Dist: DateTime (==4.3)
Requires-Dist: dispatch (==1.3.9)
Requires-Dist: distutils-pytest (==0.1)
Requires-Dist: future (==0.18.2)
Requires-Dist: Pillow (==7.2.0)
Requires-Dist: pytz (==2020.1)
Requires-Dist: regex (==2020.7.14)
Requires-Dist: requests (==2.24.0)
Requires-Dist: selenium (==3.141.0)
Requires-Dist: termcolor (==1.1.0)
Requires-Dist: urllib3 (==1.25.10)
Requires-Dist: zope.interface (==5.1.0)
